{
 "aggregate_function_based_on": "",
 "color": "#EC864B",
 "creation": "2023-12-15 13:58:40.548332",
 "docstatus": 0,
 "doctype": "Number Card",
 "document_type": "Inn Reservation",
 "dynamic_filters_json": "[]",
 "filters_json": "[[\"Inn Reservation\",\"status\",\"=\",\"Finish\",false]]",
 "function": "Count",
 "idx": 1,
 "is_public": 1,
 "is_standard": 1,
 "label": "Check Out",
 "modified": "2023-12-15 14:46:58.324325",
 "modified_by": "Administrator",
 "module": "Inn Hotels",
 "name": "Check Out",
 "owner": "Administrator",
 "parent_document_type": "",
 "report_function": "Sum",
 "show_percentage_stats": 1,
 "stats_time_interval": "Daily",
 "type": "Document Type"
}